{
"type": "FeatureCollection",
"name": "Centros_de_atencion_sanitaria_Banfield",
"crs": { "type": "name", "properties": { "name": "urn:ogc:def:crs:OGC:1.3:CRS84" } },
"features": [
{ "type": "Feature", "properties": { "Nombre Ins": "Hospital Veterinario", "Servicios": null, "Detalle [x": null, "CGM": "Banfield" }, "geometry": { "type": "Point", "coordinates": [ -58.424943, -34.743801 ] } },
{ "type": "Feature", "properties": { "Nombre Ins": "CENTRO DE SALUD MENTAL Y ADICCIONES", "Servicios": null, "Detalle [x": null, "CGM": "Banfield" }, "geometry": { "type": "Point", "coordinates": [ -58.392918, -34.737204 ] } }
]
}
