{
"type": "FeatureCollection",
"name": "Comedores_Parque Baron",
"crs": { "type": "name", "properties": { "name": "urn:ogc:def:crs:OGC:1.3:CRS84" } },
"features": [
{ "type": "Feature", "properties": { "CGM": "Parque Baron", "NOMBRE": "Comedor Comunitario Ninos De Ojos Tristes Y Angelicales", "TIPO": "COMEDORES", "Fecha Vencimiento Reconocimiento": "2026-12-21T00:00:00", "LATITUD": -34.764255, "LONGITUD": -58.448873 }, "geometry": { "type": "Point", "coordinates": [ -58.448873, -34.764255 ] } },
{ "type": "Feature", "properties": { "CGM": "Parque Baron", "NOMBRE": "Merendero Comedor Los Gitanitos", "TIPO": "COMEDORES", "Fecha Vencimiento Reconocimiento": "2026-12-21T00:00:00", "LATITUD": -34.757294, "LONGITUD": -58.453187 }, "geometry": { "type": "Point", "coordinates": [ -58.453187, -34.757294 ] } },
{ "type": "Feature", "properties": { "CGM": "Parque Baron", "NOMBRE": "Comedor Comunitario Osito Blanco", "TIPO": "COMEDORES", "Fecha Vencimiento Reconocimiento": "2026-12-21T00:00:00", "LATITUD": -34.753847, "LONGITUD": -58.438808 }, "geometry": { "type": "Point", "coordinates": [ -58.438808, -34.753847 ] } }
]
}
