{
"type": "FeatureCollection",
"name": "fundaciones_Temperley",
"crs": { "type": "name", "properties": { "name": "urn:ogc:def:crs:OGC:1.3:CRS84" } },
"features": [
{ "type": "Feature", "properties": { "CGM": "Temperley", "NOMBRE": "Fundacion Suenos Celestes De Temperley", "TIPO": "FUNDACIONES", "Fecha Vencimiento Reconocimiento": "2026-12-21T00:00:00", "LATITUD": -34.77857319, "LONGITUD": -58.40491776 }, "geometry": { "type": "Point", "coordinates": [ -58.40491776, -34.77857319 ] } },
{ "type": "Feature", "properties": { "CGM": "Temperley", "NOMBRE": "Fundacion Experiencia Anicca", "TIPO": "FUNDACIONES", "Fecha Vencimiento Reconocimiento": "2026-12-21T00:00:00", "LATITUD": -34.784244, "LONGITUD": -58.40171 }, "geometry": { "type": "Point", "coordinates": [ -58.40171, -34.784244 ] } },
{ "type": "Feature", "properties": { "CGM": "Temperley", "NOMBRE": "Fundacion Crecer Juntos", "TIPO": "FUNDACIONES", "Fecha Vencimiento Reconocimiento": "2026-12-21T00:00:00", "LATITUD": -34.767212, "LONGITUD": -58.397205 }, "geometry": { "type": "Point", "coordinates": [ -58.397205, -34.767212 ] } },
{ "type": "Feature", "properties": { "CGM": "Temperley", "NOMBRE": "Fundacion Sendero", "TIPO": "FUNDACIONES", "Fecha Vencimiento Reconocimiento": "2026-12-21T00:00:00", "LATITUD": -34.767212, "LONGITUD": -58.397205 }, "geometry": { "type": "Point", "coordinates": [ -58.397205, -34.767212 ] } }
]
}
