{
"type": "FeatureCollection",
"name": "fundaciones_Fiorito",
"crs": { "type": "name", "properties": { "name": "urn:ogc:def:crs:OGC:1.3:CRS84" } },
"features": [
{ "type": "Feature", "properties": { "CGM": "Fiorito", "NOMBRE": "Fundacion Hermana Maria Teresa Durand Centro Infanto Juvenil", "TIPO": "FUNDACIONES", "Fecha Vencimiento Reconocimiento": "2026-12-21T00:00:00", "LATITUD": -34.70151909, "LONGITUD": -58.4411425 }, "geometry": { "type": "Point", "coordinates": [ -58.4411425, -34.70151909 ] } }
]
}
