{
"type": "FeatureCollection",
"name": "lpr_Turdera",
"crs": { "type": "name", "properties": { "name": "urn:ogc:def:crs:OGC:1.3:CRS84" } },
"features": [
{ "type": "Feature", "properties": { "Name": "LPR20", "Ubicacion": "LPR - Yrigoyen y Segurola", "CGM": "Turdera" }, "geometry": { "type": "Point", "coordinates": [ -58.40834, -34.797729, 0.0 ] } }
]
}
