{
"type": "FeatureCollection",
"name": "parques_municipales_Turdera",
"crs": { "type": "name", "properties": { "name": "urn:ogc:def:crs:OGC:1.3:CRS84" } },
"features": [
{ "type": "Feature", "properties": { "NOMBRE": "Parque Municipal Finky", "DIRECCION": "Vicente López y San Basilio", "CGM": "Turdera" }, "geometry": { "type": "Point", "coordinates": [ -58.39921, -34.78566 ] } }
]
}
