{
"type": "FeatureCollection",
"name": "potreros_Banfield",
"crs": { "type": "name", "properties": { "name": "urn:ogc:def:crs:OGC:1.3:CRS84" } },
"features": [
{ "type": "Feature", "properties": { "CGM": "Banfield", "Potrero": "Villa Niza", "Dimensiones": "", "Direccion": "Monteagudo y Gutierrez ", "Lat_Long": "-34.74538303140085, -58.42279372036234", "Tipo_de_Intervenci__n": "Pintada y luces.", "Presupuesto__SP_": "$250.00", "Informaci__n_Adicional": "N/A" }, "geometry": { "type": "Point", "coordinates": [ -58.4227937203623, -34.745383031400799, 0.0 ] } }
]
}
