{
"type": "FeatureCollection",
"name": "semaforos_solicitudes_Centenario",
"crs": { "type": "name", "properties": { "name": "urn:ogc:def:crs:OGC:1.3:CRS84" } },
"features": [
{ "type": "Feature", "properties": { "Name": "Avenida 12 de Octubre & Carlos Glade", "CGM": "Centenario" }, "geometry": { "type": "Point", "coordinates": [ -58.4261899, -34.7382726, 0.0 ] } }
]
}
