{
"type": "FeatureCollection",
"name": "semaforos_solicitudes_Lamadrid",
"crs": { "type": "name", "properties": { "name": "urn:ogc:def:crs:OGC:1.3:CRS84" } },
"features": [
{ "type": "Feature", "properties": { "Name": "Epecuén & Arana Goiri", "CGM": "Lamadrid" }, "geometry": { "type": "Point", "coordinates": [ -58.4686847, -34.7301949, 0.0 ] } }
]
}
