{
"type": "FeatureCollection",
"name": "sociedades_de_fomento_Santa Marta",
"crs": { "type": "name", "properties": { "name": "urn:ogc:def:crs:OGC:1.3:CRS84" } },
"features": [
{ "type": "Feature", "properties": { "CGM": "Santa Marta", "NOMBRE": "Sociedad De Fomento Barrio Las Heras", "TIPO": "SOCIEDADES DE FOMENTO", "Fecha Vencimiento Reconocimiento": "2026-12-21T00:00:00", "LATITUD": -34.74681541, "LONGITUD": -58.43743427 }, "geometry": { "type": "Point", "coordinates": [ -58.43743427, -34.74681541 ] } },
{ "type": "Feature", "properties": { "CGM": "Santa Marta", "NOMBRE": "Sociedad De Fomento Y Cultura Lisandro De La Torre", "TIPO": "SOCIEDADES DE FOMENTO", "Fecha Vencimiento Reconocimiento": "2026-12-21T00:00:00", "LATITUD": -34.747491, "LONGITUD": -58.445114 }, "geometry": { "type": "Point", "coordinates": [ -58.445114, -34.747491 ] } },
{ "type": "Feature", "properties": { "CGM": "Santa Marta", "NOMBRE": "Sociedad De Fomento 824 Sueños", "TIPO": "SOCIEDADES DE FOMENTO", "Fecha Vencimiento Reconocimiento": "2026-12-21T00:00:00", "LATITUD": -34.73834592, "LONGITUD": -58.43491766 }, "geometry": { "type": "Point", "coordinates": [ -58.43491766, -34.73834592 ] } }
]
}
